rbacx/__init__.py
rbacx/cli.py
rbacx/py.typed
rbacx/adapters/__init__.py
rbacx/adapters/_common.py
rbacx/adapters/asgi.py
rbacx/adapters/asgi_accesslog.py
rbacx/adapters/asgi_logging.py
rbacx/adapters/drf.py
rbacx/adapters/fastapi.py
rbacx/adapters/flask.py
rbacx/adapters/litestar.py
rbacx/adapters/litestar_guard.py
rbacx/adapters/starlette.py
rbacx/adapters/django/__init__.py
rbacx/adapters/django/decorators.py
rbacx/adapters/django/middleware.py
rbacx/adapters/django/trace.py
rbacx/core/__init__.py
rbacx/core/cache.py
rbacx/core/compiler.py
rbacx/core/decision.py
rbacx/core/engine.py
rbacx/core/helpers.py
rbacx/core/model.py
rbacx/core/obligations.py
rbacx/core/policy.py
rbacx/core/policyset.py
rbacx/core/ports.py
rbacx/core/relctx.py
rbacx/core/roles.py
rbacx/dsl/lint.py
rbacx/dsl/policy.schema.json
rbacx/dsl/validate.py
rbacx/logging/__init__.py
rbacx/logging/context.py
rbacx/logging/decision_logger.py
rbacx/metrics/otel.py
rbacx/metrics/prometheus.py
rbacx/obligations/enforcer.py
rbacx/policy/__init__.py
rbacx/policy/loader.py
rbacx/rebac/__init__.py
rbacx/rebac/helpers.py
rbacx/rebac/local.py
rbacx/rebac/openfga.py
rbacx/rebac/spicedb.py
rbacx/storage/__init__.py
rbacx/storage/s3.py
rbacx/store/__init__.py
rbacx/store/file_store.py
rbacx/store/http_store.py
rbacx/store/manager.py
rbacx/store/policy_loader.py
rbacx/store/s3_store.py
rbacx-1.8.0.dist-info/licenses/LICENSE
rbacx-1.8.0.dist-info/METADATA
rbacx-1.8.0.dist-info/WHEEL
rbacx-1.8.0.dist-info/entry_points.txt
rbacx-1.8.0.dist-info/top_level.txt
rbacx-1.8.0.dist-info/RECORD
