Metadata-Version: 2.4
Name: rbacx
Version: 1.8.0
Summary: RBAC/ABAC policy engine for Python with policy sets, condition DSL, and hot reload
Author-email: Cheater121 <cheater1211@gmail.com>
License: 
Project-URL: Homepage, https://github.com/Cheater121/rbacx
Project-URL: Repository, https://github.com/Cheater121/rbacx
Project-URL: Issues, https://github.com/Cheater121/rbacx/issues
Project-URL: Changelog, https://github.com/Cheater121/rbacx/blob/main/CHANGELOG.md
Project-URL: Documentation, https://cheater121.github.io/rbacx/
Keywords: rbac,abac,policy,authorization
Classifier: Programming Language :: Python :: 3.10
Classifier: Programming Language :: Python :: 3.11
Classifier: Programming Language :: Python :: 3.12
Classifier: Programming Language :: Python :: 3.13
Classifier: Development Status :: 5 - Production/Stable
Classifier: License :: OSI Approved :: MIT License
Classifier: Typing :: Typed
Requires-Python: >=3.10
License-File: LICENSE
Provides-Extra: yaml
Requires-Dist: PyYAML>=6.0; extra == "yaml"
Provides-Extra: adapters-fastapi
Requires-Dist: fastapi>=0.110; extra == "adapters-fastapi"
Requires-Dist: starlette>=0.37; extra == "adapters-fastapi"
Provides-Extra: adapters-flask
Requires-Dist: flask>=2.3; extra == "adapters-flask"
Provides-Extra: adapters-drf
Requires-Dist: django>=4.2; extra == "adapters-drf"
Requires-Dist: djangorestframework>=3.14; extra == "adapters-drf"
Provides-Extra: adapters-litestar
Requires-Dist: litestar>=2.8; extra == "adapters-litestar"
Provides-Extra: metrics
Requires-Dist: prometheus-client>=0.14; extra == "metrics"
Requires-Dist: opentelemetry-api>=1.25; extra == "metrics"
Provides-Extra: dates
Requires-Dist: python-dateutil>=2.8; extra == "dates"
Provides-Extra: http
Requires-Dist: requests>=2.28; extra == "http"
Provides-Extra: s3
Requires-Dist: boto3>=1.26; extra == "s3"
Provides-Extra: otel
Requires-Dist: opentelemetry-api>=1.25; extra == "otel"
Requires-Dist: opentelemetry-sdk>=1.19; extra == "otel"
Provides-Extra: dev
Requires-Dist: pytest; extra == "dev"
Requires-Dist: pytest-cov; extra == "dev"
Requires-Dist: pre-commit>=3.7; extra == "dev"
Requires-Dist: build>=1.2; extra == "dev"
Requires-Dist: ruff>=0.6; extra == "dev"
Requires-Dist: twine; extra == "dev"
Requires-Dist: mypy>=1.8; extra == "dev"
Requires-Dist: pytest-asyncio>=1.1.0; extra == "dev"
Provides-Extra: tests
Requires-Dist: pytest>=8; extra == "tests"
Requires-Dist: pytest-asyncio>=1.1.0; extra == "tests"
Requires-Dist: coverage>=7; extra == "tests"
Requires-Dist: hypothesis>=6.140.0; extra == "tests"
Provides-Extra: docs
Requires-Dist: mkdocs<1.7,>=1.6.1; extra == "docs"
Requires-Dist: mkdocs-material<10,>=9.5.19; extra == "docs"
Requires-Dist: mkdocs-autorefs<2,>=1.4.2; extra == "docs"
Requires-Dist: mkdocstrings[python]<1,>=0.26.2; extra == "docs"
Provides-Extra: examples
Requires-Dist: uvicorn>=0.30; extra == "examples"
Requires-Dist: fastapi>=0.110; extra == "examples"
Requires-Dist: starlette>=0.37; extra == "examples"
Requires-Dist: flask>=2.3; extra == "examples"
Requires-Dist: django>=4.2; extra == "examples"
Requires-Dist: djangorestframework>=3.14; extra == "examples"
Requires-Dist: litestar>=2.8; extra == "examples"
Provides-Extra: validate
Requires-Dist: jsonschema>=4.18; extra == "validate"
Provides-Extra: rebac-openfga
Requires-Dist: httpx>=0.25; extra == "rebac-openfga"
Provides-Extra: rebac-spicedb
Requires-Dist: authzed>=1.22; extra == "rebac-spicedb"
Requires-Dist: grpcio>=1.60; extra == "rebac-spicedb"
Dynamic: license-file
